setup.py
funsliders/__init__.py
funsliders/funsliders.py
funsliders.egg-info/PKG-INFO
funsliders.egg-info/SOURCES.txt
funsliders.egg-info/dependency_links.txt
funsliders.egg-info/top_level.txt