Metadata-Version: 1.0
Name: funsliders
Version: 0.0.0.4
Summary: Funsliders are user-friendly Matplotlib sliders
Home-page: UNKNOWN
Author: Zulko 2013
Author-email: UNKNOWN
License: This is free and unencumbered software released into the public domain.
